Metadata-Version: 2.1
Name: audio-separator-fork
Version: 0.8.11
Summary: Easy to use vocal separation on CLI or as a python package, using the amazing MDX-Net models from UVR trained by @Anjok07
Home-page: https://github.com/karaokenerds/python-audio-separator
License: MIT
Author: Andrew Beveridge
Author-email: andrew@beveridge.uk
Requires-Python: >=3.9
Classifier: License :: OSI Approved :: MIT License
Classifier: Programming Language :: Python :: 3
Classifier: Programming Language :: Python :: 3.9
Classifier: Programming Language :: Python :: 3.10
Classifier: Programming Language :: Python :: 3.11
Classifier: Programming Language :: Python :: 3.12
Requires-Dist: librosa (>=0.9,<0.10)
Requires-Dist: numpy (>=1.23,<2.0)
Requires-Dist: onnx (>=1.14,<2.0)
Requires-Dist: onnx2torch (>=1.5.13,<2.0.0)
Requires-Dist: onnxruntime-silicon (>=1.15,<2.0) ; sys_platform == "darwin" and platform_machine == "arm64"
Requires-Dist: six (>=1.16,<2.0)
Requires-Dist: soundfile (>=0.11,<0.12)
Requires-Dist: torch (>=2,<3)
Requires-Dist: wget (>=3,<4)
Project-URL: Documentation, https://github.com/karaokenerds/python-audio-separator/blob/main/README.md
Project-URL: Repository, https://github.com/karaokenerds/python-audio-separator
